LICENSE
MANIFEST.in
README.md
pyproject.toml
setup.py
deterrers_cli.egg-info/PKG-INFO
deterrers_cli.egg-info/SOURCES.txt
deterrers_cli.egg-info/dependency_links.txt
deterrers_cli.egg-info/entry_points.txt
deterrers_cli.egg-info/requires.txt
deterrers_cli.egg-info/top_level.txt
deterrerscli/__main__.py
deterrerscli/types.py