Metadata-Version: 2.1
Name: deterrers-cli
Version: 0.8
Summary: Command line client for DETERRERS
Author-email: Lars Kiesow <lkiesow@uos.de>
License: MIT
Project-URL: Homepage, https://github.com/virtUOS/deterrers-cli
Project-URL: Repository, https://github.com/virtUOS/deterrers-cli
Requires-Python: >=3.10
License-File: LICENSE
Requires-Dist: deterrers-api>=0.5
Requires-Dist: PyYAML
Requires-Dist: Click
